stackoverflow_jobs/__init__.py
stackoverflow_jobs/filters.py
stackoverflow_jobs/query.py
stackoverflow_jobs-0.1.0.dist-info/LICENSE
stackoverflow_jobs-0.1.0.dist-info/METADATA
stackoverflow_jobs-0.1.0.dist-info/WHEEL
stackoverflow_jobs-0.1.0.dist-info/top_level.txt
stackoverflow_jobs-0.1.0.dist-info/RECORD
