Metadata-Version: 2.1
Name: stackoverflow-jobs
Version: 0.1.0
Summary: Simple wrapper for crawling jobs data at Stack Overflow Jobs portal.
Home-page: https://github.com/jemaf/stackoverflow-jobs
Author: João Eduardo Montandon
Author-email: edu.montandon@gmail.com
License: MIT
Keywords: Stack Overflow,Jobs,crawler
Platform: UNKNOWN
Classifier: Development Status :: 3 - Alpha
Classifier: Intended Audience :: Developers
Classifier: Natural Language :: English
Classifier: License :: OSI Approved :: MIT License
Classifier: Operating System :: OS Independent
Classifier: Programming Language :: Python :: 3
Classifier: Topic :: Software Development :: Libraries :: Python Modules
Requires-Python: >=3
Requires-Dist: requests
